{
  "experiment": 1,
  "n_observations": 2048,
  "n_factors": 11,
  "factors": [
    "auction_type_coded",
    "alpha_coded",
    "gamma_coded",
    "reserve_price_coded",
    "init_coded",
    "exploration_coded",
    "asynchronous_coded",
    "n_bidders_coded",
    "n_actions_coded",
    "info_feedback_coded",
    "decay_type_coded"
  ],
  "responses": {
    "avg_rev_last_1000": {
      "r_squared": 0.8094275364655532,
      "adj_r_squared": 0.803078327685506,
      "f_statistic": 127.48478818482594,
      "f_pvalue": 0.0,
      "n_obs": 2048,
      "coefficients": {
        "auction_type": {
          "estimate": 0.055269555664062615,
          "std_err": 0.001960156551546265,
          "t_value": 28.196500744016262,
          "p_value": 2.3708460417895162e-147
        },
        "alpha": {
          "estimate": 0.004324047851562336,
          "std_err": 0.0019601565515462633,
          "t_value": 2.205970665022304,
          "p_value": 0.027500471192177994
        },
        "gamma": {
          "estimate": -0.033656176757812455,
          "std_err": 0.0019601565515462637,
          "t_value": -17.170147318724556,
          "p_value": 1.0372735877667028e-61
        },
        "reserve_price": {
          "estimate": 0.01979313964843744,
          "std_err": 0.0019601565515462633,
          "t_value": 10.097734098240105,
          "p_value": 2.061302831990618e-23
        },
        "init": {
          "estimate": -0.007070922851562497,
          "std_err": 0.0019601565515462633,
          "t_value": -3.6073255710033068,
          "p_value": 0.00031703413038893777
        },
        "exploration": {
          "estimate": -0.08786657714843817,
          "std_err": 0.001960156551546264,
          "t_value": -44.82630587803043,
          "p_value": 1.4446010304767916e-303
        },
        "asynchronous": {
          "estimate": -0.017981372070311977,
          "std_err": 0.0019601565515462624,
          "t_value": -9.173436711535839,
          "p_value": 1.1155348530968833e-19
        },
        "n_bidders": {
          "estimate": 0.11267028808593807,
          "std_err": 0.0019601565515462633,
          "t_value": 57.480249726512135,
          "p_value": 0.0
        },
        "n_actions": {
          "estimate": -0.0002472900390617927,
          "std_err": 0.0019601565515462633,
          "t_value": -0.12615831060367028,
          "p_value": 0.8996194131709286
        },
        "info_feedback": {
          "estimate": 0.011507983398438143,
          "std_err": 0.0019601565515462637,
          "t_value": 5.870951169364561,
          "p_value": 5.068275669684752e-09
        },
        "decay_type": {
          "estimate": -0.0023035888671875436,
          "std_err": 0.0019601565515462637,
          "t_value": -1.1752065748882987,
          "p_value": 0.2400533101538065
        },
        "auction_type:alpha": {
          "estimate": 0.0014564208984375125,
          "std_err": 0.0019601565515462637,
          "t_value": 0.7430125401405409,
          "p_value": 0.4575621888961209
        },
        "auction_type:gamma": {
          "estimate": -0.009300561523437495,
          "std_err": 0.0019601565515462637,
          "t_value": -4.7448054677575495,
          "p_value": 2.2362500493988048e-06
        },
        "auction_type:reserve_price": {
          "estimate": -0.01447429199218743,
          "std_err": 0.0019601565515462637,
          "t_value": -7.384253048956435,
          "p_value": 2.2461983896229751e-13
        },
        "auction_type:init": {
          "estimate": 0.004403735351562582,
          "std_err": 0.0019601565515462637,
          "t_value": 2.2466243056396227,
          "p_value": 0.024773783063919544
        },
        "auction_type:exploration": {
          "estimate": 0.041818823242187504,
          "std_err": 0.0019601565515462633,
          "t_value": 21.334430257215352,
          "p_value": 4.457640150253635e-91
        },
        "auction_type:asynchronous": {
          "estimate": -0.0002746826171875498,
          "std_err": 0.0019601565515462637,
          "t_value": -0.14013299956621691,
          "p_value": 0.8885691538413633
        },
        "auction_type:n_bidders": {
          "estimate": -0.03043903808593755,
          "std_err": 0.0019601565515462637,
          "t_value": -15.528881130400428,
          "p_value": 2.0878646342668148e-51
        },
        "auction_type:n_actions": {
          "estimate": 0.0033369384765624373,
          "std_err": 0.0019601565515462637,
          "t_value": 1.7023836560044672,
          "p_value": 0.08884035735340727
        },
        "auction_type:info_feedback": {
          "estimate": 0.005702172851562517,
          "std_err": 0.0019601565515462637,
          "t_value": 2.9090395086373966,
          "p_value": 0.0036658089717230753
        },
        "auction_type:decay_type": {
          "estimate": 0.0017025146484375385,
          "std_err": 0.0019601565515462637,
          "t_value": 0.8685605479289472,
          "p_value": 0.38519275172314227
        },
        "alpha:gamma": {
          "estimate": 0.001226391601562571,
          "std_err": 0.0019601565515462637,
          "t_value": 0.6256600273050311,
          "p_value": 0.5316100281328937
        },
        "alpha:reserve_price": {
          "estimate": 0.00021408691406250434,
          "std_err": 0.0019601565515462637,
          "t_value": 0.10921929368020249,
          "p_value": 0.9130396195383716
        },
        "alpha:init": {
          "estimate": 0.004291333007812461,
          "std_err": 0.0019601565515462637,
          "t_value": 2.189280751288593,
          "p_value": 0.0286927580966682
        },
        "alpha:exploration": {
          "estimate": -0.0040967041015624525,
          "std_err": 0.0019601565515462633,
          "t_value": -2.0899882197321333,
          "p_value": 0.0367460914444976
        },
        "alpha:asynchronous": {
          "estimate": 0.0024398681640624667,
          "std_err": 0.0019601565515462637,
          "t_value": 1.2447312752329827,
          "p_value": 0.21337777843758235
        },
        "alpha:n_bidders": {
          "estimate": 0.0009790283203124628,
          "std_err": 0.0019601565515462637,
          "t_value": 0.4994643512224364,
          "p_value": 0.617507759742806
        },
        "alpha:n_actions": {
          "estimate": 0.0024927978515624748,
          "std_err": 0.0019601565515462633,
          "t_value": 1.2717340610350938,
          "p_value": 0.20361690179801
        },
        "alpha:info_feedback": {
          "estimate": -0.0015217529296875309,
          "std_err": 0.0019601565515462637,
          "t_value": -0.776342546970088,
          "p_value": 0.4376394368498109
        },
        "alpha:decay_type": {
          "estimate": 0.000525366210937525,
          "std_err": 0.0019601565515462637,
          "t_value": 0.2680225773411269,
          "p_value": 0.7887098441786802
        },
        "gamma:reserve_price": {
          "estimate": 0.0034302490234374883,
          "std_err": 0.0019601565515462633,
          "t_value": 1.7499872756242594,
          "p_value": 0.08027532696292053
        },
        "gamma:init": {
          "estimate": -0.0048274658203124755,
          "std_err": 0.0019601565515462633,
          "t_value": -2.4627960539704565,
          "p_value": 0.013870352797668985
        },
        "gamma:exploration": {
          "estimate": 0.033902954101562445,
          "std_err": 0.0019601565515462637,
          "t_value": 17.296044070979026,
          "p_value": 1.5622653594415142e-62
        },
        "gamma:asynchronous": {
          "estimate": -0.0037752197265624164,
          "std_err": 0.0019601565515462637,
          "t_value": -1.9259786793990232,
          "p_value": 0.05424998986534426
        },
        "gamma:n_bidders": {
          "estimate": 0.02238015136718744,
          "std_err": 0.0019601565515462637,
          "t_value": 11.41753261979658,
          "p_value": 2.7542286817554347e-29
        },
        "gamma:n_actions": {
          "estimate": -0.0009536376953125361,
          "std_err": 0.0019601565515462637,
          "t_value": -0.48651098533954434,
          "p_value": 0.6266587355542378
        },
        "gamma:info_feedback": {
          "estimate": 0.0013290771484374673,
          "std_err": 0.0019601565515462637,
          "t_value": 0.6780464281738255,
          "p_value": 0.4978214440405756
        },
        "gamma:decay_type": {
          "estimate": -0.0018129638671874268,
          "std_err": 0.0019601565515462633,
          "t_value": -0.9249076895196335,
          "p_value": 0.3551265768755725
        },
        "reserve_price:init": {
          "estimate": -0.00038703613281248697,
          "std_err": 0.0019601565515462633,
          "t_value": -0.19745164359814768,
          "p_value": 0.8434943761224606
        },
        "reserve_price:exploration": {
          "estimate": -0.009928100585937523,
          "std_err": 0.0019601565515462637,
          "t_value": -5.064952887617966,
          "p_value": 4.4638241159583714e-07
        },
        "reserve_price:asynchronous": {
          "estimate": 0.004068823242187441,
          "std_err": 0.0019601565515462637,
          "t_value": 2.0757644275799105,
          "p_value": 0.03804447190000784
        },
        "reserve_price:n_bidders": {
          "estimate": -0.0181340087890625,
          "std_err": 0.0019601565515462637,
          "t_value": -9.251306368747711,
          "p_value": 5.562835836172117e-20
        },
        "reserve_price:n_actions": {
          "estimate": -0.0006982666015625096,
          "std_err": 0.0019601565515462637,
          "t_value": -0.35623001694006734,
          "p_value": 0.7217062478847209
        },
        "reserve_price:info_feedback": {
          "estimate": -0.003961450195312531,
          "std_err": 0.0019601565515462633,
          "t_value": -2.0209866360865685,
          "p_value": 0.043415424829802485
        },
        "reserve_price:decay_type": {
          "estimate": 0.0005413330078124362,
          "std_err": 0.0019601565515462637,
          "t_value": 0.27616825165592374,
          "p_value": 0.7824476479220521
        },
        "init:exploration": {
          "estimate": 0.0044020751953125865,
          "std_err": 0.0019601565515462637,
          "t_value": 2.245777354793433,
          "p_value": 0.02482810626526011
        },
        "init:asynchronous": {
          "estimate": -0.006352172851562471,
          "std_err": 0.0019601565515462637,
          "t_value": -3.240645675240367,
          "p_value": 0.0012123654915612955
        },
        "init:n_bidders": {
          "estimate": -0.003701391601562489,
          "std_err": 0.0019601565515462633,
          "t_value": -1.8883142770625427,
          "p_value": 0.05912976872424151
        },
        "init:n_actions": {
          "estimate": -0.0030582275390624923,
          "std_err": 0.0019601565515462637,
          "t_value": -1.560195555120339,
          "p_value": 0.11887340474391776
        },
        "init:info_feedback": {
          "estimate": -0.004986840820312538,
          "std_err": 0.0019601565515462637,
          "t_value": -2.5441033352048756,
          "p_value": 0.011031221172914076
        },
        "init:decay_type": {
          "estimate": -0.00015407714843746644,
          "std_err": 0.0019601565515462637,
          "t_value": -0.07860451162225952,
          "p_value": 0.9373551375816985
        },
        "exploration:asynchronous": {
          "estimate": 0.018276391601561918,
          "std_err": 0.0019601565515462633,
          "t_value": 9.323944858967844,
          "p_value": 2.89300740337252e-20
        },
        "exploration:n_bidders": {
          "estimate": -0.016810815429687966,
          "std_err": 0.0019601565515462637,
          "t_value": -8.576261634014285,
          "p_value": 1.9430584147835172e-17
        },
        "exploration:n_actions": {
          "estimate": -0.00455739746093798,
          "std_err": 0.0019601565515462637,
          "t_value": -2.3250170795505545,
          "p_value": 0.020171623217419554
        },
        "exploration:info_feedback": {
          "estimate": -0.010880151367187986,
          "std_err": 0.0019601565515462637,
          "t_value": -5.550654287590045,
          "p_value": 3.2287818208032456e-08
        },
        "exploration:decay_type": {
          "estimate": 0.0023463623046875333,
          "std_err": 0.0019601565515462633,
          "t_value": 1.1970280143372287,
          "p_value": 0.2314388597612878
        },
        "asynchronous:n_bidders": {
          "estimate": 0.008845288085936969,
          "std_err": 0.0019601565515462633,
          "t_value": 4.512541653348755,
          "p_value": 6.7812312780262704e-06
        },
        "asynchronous:n_actions": {
          "estimate": -0.002378051757812971,
          "std_err": 0.0019601565515462633,
          "t_value": -1.2131948113721083,
          "p_value": 0.2251999851116254
        },
        "asynchronous:info_feedback": {
          "estimate": -0.015803442382812942,
          "std_err": 0.0019601565515462637,
          "t_value": -8.062336842609048,
          "p_value": 1.2816754160328234e-15
        },
        "asynchronous:decay_type": {
          "estimate": 0.0022843994140625337,
          "std_err": 0.0019601565515462633,
          "t_value": 1.16541681951908,
          "p_value": 0.24399061608791694
        },
        "n_bidders:n_actions": {
          "estimate": -0.0012638916015632051,
          "std_err": 0.0019601565515462637,
          "t_value": -0.6447911523016812,
          "p_value": 0.5191371955940933
        },
        "n_bidders:info_feedback": {
          "estimate": -0.01801340332031308,
          "std_err": 0.0019601565515462637,
          "t_value": -9.18977788080409,
          "p_value": 9.644018927896589e-20
        },
        "n_bidders:decay_type": {
          "estimate": 0.00319582519531254,
          "std_err": 0.0019601565515462633,
          "t_value": 1.630392834078239,
          "p_value": 0.10317746736334936
        },
        "n_actions:info_feedback": {
          "estimate": 0.0006331787109370018,
          "std_err": 0.0019601565515462637,
          "t_value": 0.3230245617052988,
          "p_value": 0.7467107324563522
        },
        "n_actions:decay_type": {
          "estimate": 0.0005016845703124232,
          "std_err": 0.0019601565515462637,
          "t_value": 0.25594107262334265,
          "p_value": 0.7980229120640668
        },
        "info_feedback:decay_type": {
          "estimate": -0.0011430419921875637,
          "std_err": 0.0019601565515462633,
          "t_value": -0.583138112762411,
          "p_value": 0.5598667044852446
        }
      }
    },
    "time_to_converge": {
      "r_squared": 0.6766886355339079,
      "adj_r_squared": 0.6659170302563904,
      "f_statistic": 62.82152177877288,
      "f_pvalue": 0.0,
      "n_obs": 2048,
      "coefficients": {
        "auction_type": {
          "estimate": -8050.245605468801,
          "std_err": 499.1563163306625,
          "t_value": -16.127704572881683,
          "p_value": 4.478372691599188e-55
        },
        "alpha": {
          "estimate": 228.29248046875801,
          "std_err": 499.15631633066204,
          "t_value": 0.4573566896778033,
          "p_value": 0.6474648407381636
        },
        "gamma": {
          "estimate": 3718.399902343748,
          "std_err": 499.15631633066215,
          "t_value": 7.449369627690985,
          "p_value": 1.392473248520204e-13
        },
        "reserve_price": {
          "estimate": 235.45556640625006,
          "std_err": 499.15631633066204,
          "t_value": 0.4717070759258397,
          "p_value": 0.637187833873424
        },
        "init": {
          "estimate": 864.1381835937516,
          "std_err": 499.156316330662,
          "t_value": 1.7311975333620948,
          "p_value": 0.08357223640393611
        },
        "exploration": {
          "estimate": -11403.79345703129,
          "std_err": 499.15631633066226,
          "t_value": -22.846136739010902,
          "p_value": 9.793027725114117e-103
        },
        "asynchronous": {
          "estimate": 1384.2016601563223,
          "std_err": 499.15631633066175,
          "t_value": 2.773082529199871,
          "p_value": 0.005604811827746923
        },
        "n_bidders": {
          "estimate": -26110.67333984372,
          "std_err": 499.15631633066204,
          "t_value": -52.3096122108308,
          "p_value": 0.0
        },
        "n_actions": {
          "estimate": 1530.0151367187827,
          "std_err": 499.15631633066204,
          "t_value": 3.0652023958467485,
          "p_value": 0.002204583319753124
        },
        "info_feedback": {
          "estimate": 1348.7446289062882,
          "std_err": 499.1563163306621,
          "t_value": 2.702048606378494,
          "p_value": 0.006950150859959151
        },
        "decay_type": {
          "estimate": -4108.860839843746,
          "std_err": 499.1563163306621,
          "t_value": -8.231611431962456,
          "p_value": 3.309735305458175e-16
        },
        "auction_type:alpha": {
          "estimate": 737.3579101562505,
          "std_err": 499.15631633066215,
          "t_value": 1.4772084135419286,
          "p_value": 0.13977873060867807
        },
        "auction_type:gamma": {
          "estimate": 773.92236328125,
          "std_err": 499.1563163306621,
          "t_value": 1.5504609236850193,
          "p_value": 0.12119065804198972
        },
        "auction_type:reserve_price": {
          "estimate": 4852.853027343747,
          "std_err": 499.1563163306621,
          "t_value": 9.722110826959893,
          "p_value": 7.408723837212151e-22
        },
        "auction_type:init": {
          "estimate": -978.9760742187407,
          "std_err": 499.1563163306621,
          "t_value": -1.961261517063977,
          "p_value": 0.049988412154283034
        },
        "auction_type:exploration": {
          "estimate": -879.8334960937543,
          "std_err": 499.15631633066204,
          "t_value": -1.7626412154041857,
          "p_value": 0.0781152006995949
        },
        "auction_type:asynchronous": {
          "estimate": 282.47802734375034,
          "std_err": 499.1563163306621,
          "t_value": 0.5659109543484672,
          "p_value": 0.5715184093240882
        },
        "auction_type:n_bidders": {
          "estimate": 1665.6557617187502,
          "std_err": 499.1563163306621,
          "t_value": 3.3369421706673346,
          "p_value": 0.0008627171611887718
        },
        "auction_type:n_actions": {
          "estimate": 425.18994140624386,
          "std_err": 499.1563163306621,
          "t_value": 0.8518172113534475,
          "p_value": 0.39441851275460804
        },
        "auction_type:info_feedback": {
          "estimate": 420.80224609376285,
          "std_err": 499.1563163306621,
          "t_value": 0.8430269883933629,
          "p_value": 0.3993151238743573
        },
        "auction_type:decay_type": {
          "estimate": -648.9672851562462,
          "std_err": 499.1563163306621,
          "t_value": -1.3001283644507526,
          "p_value": 0.19370822189109033
        },
        "alpha:gamma": {
          "estimate": 482.5620117187521,
          "std_err": 499.1563163306621,
          "t_value": 0.9667552947463511,
          "p_value": 0.3337843836833423
        },
        "alpha:reserve_price": {
          "estimate": -457.429199218744,
          "std_err": 499.1563163306621,
          "t_value": -0.9164047098138365,
          "p_value": 0.35956620883324597
        },
        "alpha:init": {
          "estimate": -331.37353515625017,
          "std_err": 499.15631633066215,
          "t_value": -0.6638672582412729,
          "p_value": 0.5068525265987937
        },
        "alpha:exploration": {
          "estimate": -1802.6899414062532,
          "std_err": 499.15631633066204,
          "t_value": -3.6114737656892153,
          "p_value": 0.0003120378962851475
        },
        "alpha:asynchronous": {
          "estimate": 227.9731445312567,
          "std_err": 499.1563163306621,
          "t_value": 0.45671693830723303,
          "p_value": 0.6479245864401622
        },
        "alpha:n_bidders": {
          "estimate": -920.6225585937513,
          "std_err": 499.1563163306621,
          "t_value": -1.8443572253303757,
          "p_value": 0.06528031852840105
        },
        "alpha:n_actions": {
          "estimate": 167.34912109375338,
          "std_err": 499.15631633066204,
          "t_value": 0.3352639556360824,
          "p_value": 0.7374614793002618
        },
        "alpha:info_feedback": {
          "estimate": 1267.098144531242,
          "std_err": 499.1563163306621,
          "t_value": 2.5384796366913305,
          "p_value": 0.011209505197562203
        },
        "alpha:decay_type": {
          "estimate": -237.97998046874318,
          "std_err": 499.1563163306621,
          "t_value": -0.47676443767786614,
          "p_value": 0.6335824565855368
        },
        "gamma:reserve_price": {
          "estimate": -560.0795898437518,
          "std_err": 499.15631633066204,
          "t_value": -1.122052494418866,
          "p_value": 0.26197610180634245
        },
        "gamma:init": {
          "estimate": 144.06787109375426,
          "std_err": 499.15631633066204,
          "t_value": 0.28862275479715194,
          "p_value": 0.7729002770120491
        },
        "gamma:exploration": {
          "estimate": -1966.6665039062532,
          "std_err": 499.1563163306621,
          "t_value": -3.939981203410137,
          "p_value": 8.43124398300993e-05
        },
        "gamma:asynchronous": {
          "estimate": 2229.3754882812595,
          "std_err": 499.1563163306621,
          "t_value": 4.466287243782823,
          "p_value": 8.407204430677906e-06
        },
        "gamma:n_bidders": {
          "estimate": 2369.5454101562423,
          "std_err": 499.1563163306621,
          "t_value": 4.747100923363966,
          "p_value": 2.2113122695836115e-06
        },
        "gamma:n_actions": {
          "estimate": -903.0805664062491,
          "std_err": 499.1563163306621,
          "t_value": -1.8092139413257682,
          "p_value": 0.07056929926060587
        },
        "gamma:info_feedback": {
          "estimate": 1114.6391601562455,
          "std_err": 499.1563163306621,
          "t_value": 2.2330462896874606,
          "p_value": 0.025657198616027783
        },
        "gamma:decay_type": {
          "estimate": 1414.6606445312502,
          "std_err": 499.15631633066204,
          "t_value": 2.8341034626798547,
          "p_value": 0.004642015984560498
        },
        "reserve_price:init": {
          "estimate": -192.2749023437521,
          "std_err": 499.15631633066204,
          "t_value": -0.38519977821212453,
          "p_value": 0.7001307614918011
        },
        "reserve_price:exploration": {
          "estimate": 1820.586425781249,
          "std_err": 499.1563163306621,
          "t_value": 3.647327232407926,
          "p_value": 0.00027182710026432894
        },
        "reserve_price:asynchronous": {
          "estimate": -581.3696289062585,
          "std_err": 499.1563163306621,
          "t_value": -1.16470454221626,
          "p_value": 0.2442788454317724
        },
        "reserve_price:n_bidders": {
          "estimate": -1303.0551757812425,
          "std_err": 499.1563163306621,
          "t_value": -2.610515249731998,
          "p_value": 0.009108751290545631
        },
        "reserve_price:n_actions": {
          "estimate": 590.1625976562484,
          "std_err": 499.1563163306621,
          "t_value": 1.1823202038082594,
          "p_value": 0.2372205624171728
        },
        "reserve_price:info_feedback": {
          "estimate": -1246.7934570312473,
          "std_err": 499.15631633066204,
          "t_value": -2.4978016229395346,
          "p_value": 0.012577144503754472
        },
        "reserve_price:decay_type": {
          "estimate": 115.98583984374852,
          "std_err": 499.1563163306621,
          "t_value": 0.23236376271138806,
          "p_value": 0.8162794939398668
        },
        "init:exploration": {
          "estimate": -456.21142578124557,
          "std_err": 499.15631633066215,
          "t_value": -0.9139650463303602,
          "p_value": 0.36084643658319715
        },
        "init:asynchronous": {
          "estimate": 176.8071289062546,
          "std_err": 499.1563163306621,
          "t_value": 0.354211943476901,
          "p_value": 0.723217751330878
        },
        "init:n_bidders": {
          "estimate": 554.1293945312498,
          "std_err": 499.15631633066204,
          "t_value": 1.1101319895232404,
          "p_value": 0.2670768866290497
        },
        "init:n_actions": {
          "estimate": -140.93603515625028,
          "std_err": 499.1563163306621,
          "t_value": -0.28234849594267847,
          "p_value": 0.7777057984442326
        },
        "init:info_feedback": {
          "estimate": -81.3159179687496,
          "std_err": 499.1563163306621,
          "t_value": -0.16290671941509105,
          "p_value": 0.8706084958984507
        },
        "init:decay_type": {
          "estimate": 1139.2094726562532,
          "std_err": 499.1563163306621,
          "t_value": 2.282269973123195,
          "p_value": 0.022578990931239308
        },
        "exploration:asynchronous": {
          "estimate": -743.5327148437689,
          "std_err": 499.15631633066204,
          "t_value": -1.489578896465815,
          "p_value": 0.13649417789171475
        },
        "exploration:n_bidders": {
          "estimate": -4593.548339843772,
          "std_err": 499.1563163306621,
          "t_value": -9.202624888354238,
          "p_value": 8.599661130363933e-20
        },
        "exploration:n_actions": {
          "estimate": -868.91259765627,
          "std_err": 499.1563163306621,
          "t_value": -1.74076250110129,
          "p_value": 0.08188047717361
        },
        "exploration:info_feedback": {
          "estimate": -420.6674804687759,
          "std_err": 499.1563163306621,
          "t_value": -0.8427570015764523,
          "p_value": 0.39946609770559705
        },
        "exploration:decay_type": {
          "estimate": 4505.721191406251,
          "std_err": 499.15631633066204,
          "t_value": 9.026673697186018,
          "p_value": 4.0812621666382197e-19
        },
        "asynchronous:n_bidders": {
          "estimate": 2231.003417968722,
          "std_err": 499.15631633066204,
          "t_value": 4.469548606274295,
          "p_value": 8.28129764137864e-06
        },
        "asynchronous:n_actions": {
          "estimate": -161.32373046878263,
          "std_err": 499.15631633066204,
          "t_value": -0.3231928059223737,
          "p_value": 0.7465833397540753
        },
        "asynchronous:info_feedback": {
          "estimate": 1782.3120117187248,
          "std_err": 499.1563163306621,
          "t_value": 3.5706490199716243,
          "p_value": 0.0003645862413239164
        },
        "asynchronous:decay_type": {
          "estimate": 31.56201171875739,
          "std_err": 499.15631633066204,
          "t_value": 0.06323071688398588,
          "p_value": 0.9495891642973793
        },
        "n_bidders:n_actions": {
          "estimate": 39.11181640624454,
          "std_err": 499.1563163306621,
          "t_value": 0.07835584791104844,
          "p_value": 0.9375529071888801
        },
        "n_bidders:info_feedback": {
          "estimate": 625.1303710937282,
          "std_err": 499.1563163306621,
          "t_value": 1.2523739570984724,
          "p_value": 0.21058145980550563
        },
        "n_bidders:decay_type": {
          "estimate": -1653.7836914062445,
          "std_err": 499.15631633066204,
          "t_value": -3.3131578972361617,
          "p_value": 0.000939095881728886
        },
        "n_actions:info_feedback": {
          "estimate": -134.30224609377092,
          "std_err": 499.1563163306621,
          "t_value": -0.2690584927003177,
          "p_value": 0.7879126896303809
        },
        "n_actions:decay_type": {
          "estimate": 229.70556640624773,
          "std_err": 499.1563163306621,
          "t_value": 0.4601876384031994,
          "p_value": 0.6454320479609428
        },
        "info_feedback:decay_type": {
          "estimate": 251.74169921874383,
          "std_err": 499.15631633066204,
          "t_value": 0.5043343958247732,
          "p_value": 0.6140824984937631
        }
      }
    },
    "avg_regret_of_seller": {
      "r_squared": 0.9254373203304546,
      "adj_r_squared": 0.9229531523051189,
      "f_statistic": 372.53410835822933,
      "f_pvalue": 0.0,
      "n_obs": 2048,
      "coefficients": {
        "auction_type": {
          "estimate": -0.06230959741210954,
          "std_err": 0.0010002896824449503,
          "t_value": -62.291552642840216,
          "p_value": 0.0
        },
        "alpha": {
          "estimate": -0.00271994946289055,
          "std_err": 0.0010002896824449494,
          "t_value": -2.7191617694609596,
          "p_value": 0.006601867179071628
        },
        "gamma": {
          "estimate": 0.01925816674804687,
          "std_err": 0.0010002896824449496,
          "t_value": 19.2525896108168,
          "p_value": 7.424613256713048e-76
        },
        "reserve_price": {
          "estimate": -0.014230287841796814,
          "std_err": 0.0010002896824449494,
          "t_value": -14.226166771024326,
          "p_value": 8.385389819740528e-44
        },
        "init": {
          "estimate": 0.007645659912109362,
          "std_err": 0.0010002896824449492,
          "t_value": 7.643445740059545,
          "p_value": 3.273478978540036e-14
        },
        "exploration": {
          "estimate": 0.07276429907226557,
          "std_err": 0.0010002896824449499,
          "t_value": 72.74322663651996,
          "p_value": 0.0
        },
        "asynchronous": {
          "estimate": 0.012729372802734801,
          "std_err": 0.0010002896824449488,
          "t_value": 12.725686394786308,
          "p_value": 1.0225008658907559e-35
        },
        "n_bidders": {
          "estimate": -0.1039773771972653,
          "std_err": 0.0010002896824449494,
          "t_value": -103.94726549924967,
          "p_value": 0.0
        },
        "n_actions": {
          "estimate": 0.0026990666503909286,
          "std_err": 0.0010002896824449494,
          "t_value": 2.6982850045936275,
          "p_value": 0.007028927979327325
        },
        "info_feedback": {
          "estimate": -0.004582745361327779,
          "std_err": 0.0010002896824449494,
          "t_value": -4.581418204900848,
          "p_value": 4.905811617778416e-06
        },
        "decay_type": {
          "estimate": -0.012905224365234343,
          "std_err": 0.0010002896824449494,
          "t_value": -12.90148703092774,
          "p_value": 1.2612592091623993e-36
        },
        "auction_type:alpha": {
          "estimate": -0.0007319621582031215,
          "std_err": 0.0010002896824449496,
          "t_value": -0.7317501830210116,
          "p_value": 0.46440761307302414
        },
        "auction_type:gamma": {
          "estimate": 0.0013385759277343829,
          "std_err": 0.0010002896824449494,
          "t_value": 1.3381882780821854,
          "p_value": 0.18098864452078492
        },
        "auction_type:reserve_price": {
          "estimate": 0.016031720947265616,
          "std_err": 0.0010002896824449494,
          "t_value": 16.027078184071858,
          "p_value": 1.8837104672446012e-54
        },
        "auction_type:init": {
          "estimate": -0.0039690744628905926,
          "std_err": 0.0010002896824449494,
          "t_value": -3.967925024668071,
          "p_value": 7.508313610016559e-05
        },
        "auction_type:exploration": {
          "estimate": -0.035600305419921846,
          "std_err": 0.0010002896824449494,
          "t_value": -35.589995622974044,
          "p_value": 6.495493515568906e-215
        },
        "auction_type:asynchronous": {
          "estimate": -0.00375294555664058,
          "std_err": 0.0010002896824449494,
          "t_value": -3.7518587090366418,
          "p_value": 0.00018057566004102567
        },
        "auction_type:n_bidders": {
          "estimate": 0.021335693115234415,
          "std_err": 0.0010002896824449494,
          "t_value": 21.329514329373897,
          "p_value": 4.8553605842420787e-91
        },
        "auction_type:n_actions": {
          "estimate": -0.0019002360839843746,
          "std_err": 0.0010002896824449494,
          "t_value": -1.8996857783634626,
          "p_value": 0.05761947211350155
        },
        "auction_type:info_feedback": {
          "estimate": 0.0015931677246094457,
          "std_err": 0.0010002896824449494,
          "t_value": 1.592706345541183,
          "p_value": 0.11138562000150805
        },
        "auction_type:decay_type": {
          "estimate": 0.0068913352050781465,
          "std_err": 0.0010002896824449494,
          "t_value": 6.889339484372227,
          "p_value": 7.502659786330187e-12
        },
        "alpha:gamma": {
          "estimate": -0.0018430915527343503,
          "std_err": 0.0010002896824449494,
          "t_value": -1.8425577960870192,
          "p_value": 0.06554294652001691
        },
        "alpha:reserve_price": {
          "estimate": -0.00035646606445308236,
          "std_err": 0.0010002896824449494,
          "t_value": -0.3563628323965046,
          "p_value": 0.7216068093721186
        },
        "alpha:init": {
          "estimate": -0.0033051022949218754,
          "std_err": 0.0010002896824449496,
          "t_value": -3.3041451420786494,
          "p_value": 0.0009696419899058929
        },
        "alpha:exploration": {
          "estimate": 0.002115332763671871,
          "std_err": 0.0010002896824449494,
          "t_value": 2.114720166363695,
          "p_value": 0.03457839305616202
        },
        "alpha:asynchronous": {
          "estimate": -0.0027880358886718383,
          "std_err": 0.0010002896824449494,
          "t_value": -2.78722847751184,
          "p_value": 0.005366813860536618
        },
        "alpha:n_bidders": {
          "estimate": -0.000881950927734378,
          "std_err": 0.0010002896824449494,
          "t_value": -0.8816955160215959,
          "p_value": 0.3780484507837131
        },
        "alpha:n_actions": {
          "estimate": -0.0011218439941405815,
          "std_err": 0.0010002896824449494,
          "t_value": -1.1215191097428137,
          "p_value": 0.26220288758944227
        },
        "alpha:info_feedback": {
          "estimate": 0.001923685791015566,
          "std_err": 0.0010002896824449494,
          "t_value": 1.9231286943934218,
          "p_value": 0.054607082096966485
        },
        "alpha:decay_type": {
          "estimate": -0.0007710764160155807,
          "std_err": 0.0010002896824449494,
          "t_value": -0.7708531134009938,
          "p_value": 0.44088592674978466
        },
        "gamma:reserve_price": {
          "estimate": -0.0016988508300781354,
          "std_err": 0.0010002896824449494,
          "t_value": -1.698358845335417,
          "p_value": 0.08959709027842824
        },
        "gamma:init": {
          "estimate": 0.006591715087890646,
          "std_err": 0.0010002896824449494,
          "t_value": 6.589806136737213,
          "p_value": 5.6283316871782643e-11
        },
        "gamma:exploration": {
          "estimate": -0.019520618408203155,
          "std_err": 0.0010002896824449494,
          "t_value": -19.514965265351986,
          "p_value": 1.0213242628474882e-77
        },
        "gamma:asynchronous": {
          "estimate": 0.007098426025390656,
          "std_err": 0.0010002896824449494,
          "t_value": 7.096370331482766,
          "p_value": 1.7764397979611835e-12
        },
        "gamma:n_bidders": {
          "estimate": -0.0067796003417969035,
          "std_err": 0.0010002896824449494,
          "t_value": -6.777636979345747,
          "p_value": 1.6059991076614747e-11
        },
        "gamma:n_actions": {
          "estimate": 0.0007654597167968836,
          "std_err": 0.0010002896824449494,
          "t_value": 0.7652380407702649,
          "p_value": 0.44422096606875605
        },
        "gamma:info_feedback": {
          "estimate": -0.0032082888183593925,
          "std_err": 0.0010002896824449494,
          "t_value": -3.207359702558923,
          "p_value": 0.0013609683312735344
        },
        "gamma:decay_type": {
          "estimate": 0.00456667553710939,
          "std_err": 0.0010002896824449494,
          "t_value": 4.565353034480305,
          "p_value": 5.29268607733804e-06
        },
        "reserve_price:init": {
          "estimate": -0.0009303098144531163,
          "std_err": 0.0010002896824449494,
          "t_value": -0.9300403980766997,
          "p_value": 0.3524634843898866
        },
        "reserve_price:exploration": {
          "estimate": 0.0041467971191406425,
          "std_err": 0.0010002896824449494,
          "t_value": 4.1455962126939765,
          "p_value": 3.53219200006062e-05
        },
        "reserve_price:asynchronous": {
          "estimate": -0.0017042141113281502,
          "std_err": 0.0010002896824449494,
          "t_value": -1.7037205733869407,
          "p_value": 0.08859013744022015
        },
        "reserve_price:n_bidders": {
          "estimate": 0.013080729248046895,
          "std_err": 0.0010002896824449494,
          "t_value": 13.076941087780128,
          "p_value": 1.5254154634182234e-37
        },
        "reserve_price:n_actions": {
          "estimate": 0.0011338898925781118,
          "std_err": 0.0010002896824449494,
          "t_value": 1.1335615197055828,
          "p_value": 0.2571156844125058
        },
        "reserve_price:info_feedback": {
          "estimate": 0.0007919733886718647,
          "std_err": 0.0010002896824449494,
          "t_value": 0.7917440343242276,
          "p_value": 0.42860473123734355
        },
        "reserve_price:decay_type": {
          "estimate": -0.0001678991699218882,
          "std_err": 0.0010002896824449494,
          "t_value": -0.1678505465651731,
          "p_value": 0.8667179893755417
        },
        "init:exploration": {
          "estimate": -0.0045945510253906025,
          "std_err": 0.0010002896824449496,
          "t_value": -4.5932204500604366,
          "p_value": 4.63902314561867e-06
        },
        "init:asynchronous": {
          "estimate": 0.005832738525390638,
          "std_err": 0.0010002896824449494,
          "t_value": 5.8310493727517185,
          "p_value": 6.416378951009947e-09
        },
        "init:n_bidders": {
          "estimate": 0.0033077775878906507,
          "std_err": 0.0010002896824449494,
          "t_value": 3.306819660286452,
          "p_value": 0.0009604827471040413
        },
        "init:n_actions": {
          "estimate": 0.001139402099609394,
          "std_err": 0.0010002896824449494,
          "t_value": 1.1390721304096831,
          "p_value": 0.2548107900956922
        },
        "init:info_feedback": {
          "estimate": 0.004326976806640623,
          "std_err": 0.0010002896824449494,
          "t_value": 4.325723720417117,
          "p_value": 1.595908751995627e-05
        },
        "init:decay_type": {
          "estimate": 0.0012369362792968917,
          "std_err": 0.0010002896824449494,
          "t_value": 1.236578064339843,
          "p_value": 0.21639035060725267
        },
        "exploration:asynchronous": {
          "estimate": -0.012498364501953326,
          "std_err": 0.0010002896824449494,
          "t_value": -12.494744993674539,
          "p_value": 1.540650919870426e-34
        },
        "exploration:n_bidders": {
          "estimate": 0.007698195068359157,
          "std_err": 0.0010002896824449494,
          "t_value": 7.695965682204089,
          "p_value": 2.1994822296124562e-14
        },
        "exploration:n_actions": {
          "estimate": 0.0021245822753904117,
          "std_err": 0.0010002896824449494,
          "t_value": 2.1239669994370227,
          "p_value": 0.03379648869978771
        },
        "exploration:info_feedback": {
          "estimate": 0.004761793701171593,
          "std_err": 0.0010002896824449494,
          "t_value": 4.760414692604466,
          "p_value": 2.07185879175002e-06
        },
        "exploration:decay_type": {
          "estimate": 0.012887877197265625,
          "std_err": 0.0010002896824449494,
          "t_value": 12.88414488667377,
          "p_value": 1.5521111926324668e-36
        },
        "asynchronous:n_bidders": {
          "estimate": -0.0038614157714846418,
          "std_err": 0.0010002896824449494,
          "t_value": -3.8602975110634046,
          "p_value": 0.0001168791332077121
        },
        "asynchronous:n_actions": {
          "estimate": 0.0014066755371090617,
          "std_err": 0.0010002896824449494,
          "t_value": 1.4062681659085068,
          "p_value": 0.15980134616853114
        },
        "asynchronous:info_feedback": {
          "estimate": 0.012722094970702882,
          "std_err": 0.0010002896824449494,
          "t_value": 12.718410670404008,
          "p_value": 1.1144312271142922e-35
        },
        "asynchronous:decay_type": {
          "estimate": 0.002425908935546885,
          "std_err": 0.0010002896824449494,
          "t_value": 2.425206395828634,
          "p_value": 0.015388544745152171
        },
        "n_bidders:n_actions": {
          "estimate": 0.00041971264648431317,
          "std_err": 0.0010002896824449494,
          "t_value": 0.419591098309076,
          "p_value": 0.67482968995658
        },
        "n_bidders:info_feedback": {
          "estimate": 0.00888721606445297,
          "std_err": 0.0010002896824449494,
          "t_value": 8.884642339537553,
          "p_value": 1.4066040392644716e-18
        },
        "n_bidders:decay_type": {
          "estimate": 0.0020175446777343934,
          "std_err": 0.0010002896824449494,
          "t_value": 2.016960399714438,
          "p_value": 0.043834315959903516
        },
        "n_actions:info_feedback": {
          "estimate": 0.00018949877929673106,
          "std_err": 0.0010002896824449494,
          "t_value": 0.18944390072438846,
          "p_value": 0.8497643269972613
        },
        "n_actions:decay_type": {
          "estimate": -0.0008208083496093906,
          "std_err": 0.0010002896824449494,
          "t_value": -0.8205706446987805,
          "p_value": 0.4119896010066423
        },
        "info_feedback:decay_type": {
          "estimate": -0.002024460205078157,
          "std_err": 0.0010002896824449494,
          "t_value": -2.0238739243314874,
          "p_value": 0.043117118319620756
        }
      }
    },
    "no_sale_rate": {
      "r_squared": 0.9327834184263475,
      "adj_r_squared": 0.9305439967282854,
      "f_statistic": 416.528704367529,
      "f_pvalue": 0.0,
      "n_obs": 2048,
      "coefficients": {
        "auction_type": {
          "estimate": 0.0023482812500000474,
          "std_err": 0.00032720563480453225,
          "t_value": 7.176775092528207,
          "p_value": 1.0046103214856968e-12
        },
        "alpha": {
          "estimate": -0.0008498632812500043,
          "std_err": 0.0003272056348045319,
          "t_value": -2.597336936931727,
          "p_value": 0.009464532709048038
        },
        "gamma": {
          "estimate": 0.0014884765625000117,
          "std_err": 0.00032720563480453203,
          "t_value": 4.549055407891146,
          "p_value": 5.714941891012625e-06
        },
        "reserve_price": {
          "estimate": 0.03357834960937494,
          "std_err": 0.0003272056348045319,
          "t_value": 102.62155060206764,
          "p_value": 0.0
        },
        "init": {
          "estimate": 0.0015503613281250025,
          "std_err": 0.00032720563480453187,
          "t_value": 4.738186520079848,
          "p_value": 2.3096805615160034e-06
        },
        "exploration": {
          "estimate": 0.018307119140625,
          "std_err": 0.0003272056348045321,
          "t_value": 55.94988959026152,
          "p_value": 0.0
        },
        "asynchronous": {
          "estimate": 0.0011837500000000634,
          "std_err": 0.00032720563480453176,
          "t_value": 3.617755546010752,
          "p_value": 0.0003046121516573152
        },
        "n_bidders": {
          "estimate": -0.021702499999999965,
          "std_err": 0.0003272056348045319,
          "t_value": -66.32679175272986,
          "p_value": 0.0
        },
        "n_actions": {
          "estimate": 0.0022141015625000483,
          "std_err": 0.0003272056348045319,
          "t_value": 6.766697535092027,
          "p_value": 1.7292167417312557e-11
        },
        "info_feedback": {
          "estimate": 0.0005836523437500148,
          "std_err": 0.000327205634804532,
          "t_value": 1.7837478382628724,
          "p_value": 0.07461768474308135
        },
        "decay_type": {
          "estimate": -0.0026348632812499967,
          "std_err": 0.000327205634804532,
          "t_value": -8.052621963017314,
          "p_value": 1.3841614644047762e-15
        },
        "auction_type:alpha": {
          "estimate": -0.0001439941406249972,
          "std_err": 0.00032720563480453203,
          "t_value": -0.44007231327485313,
          "p_value": 0.6599327420836113
        },
        "auction_type:gamma": {
          "estimate": 0.00020872070312499662,
          "std_err": 0.000327205634804532,
          "t_value": 0.637888474169106,
          "p_value": 0.5236200048538725
        },
        "auction_type:reserve_price": {
          "estimate": 0.0023482812499999923,
          "std_err": 0.000327205634804532,
          "t_value": 7.176775092528044,
          "p_value": 1.0046103214868534e-12
        },
        "auction_type:init": {
          "estimate": 0.00015169921875000795,
          "std_err": 0.000327205634804532,
          "t_value": 0.4636204350228593,
          "p_value": 0.6429706448458311
        },
        "auction_type:exploration": {
          "estimate": 0.001895917968750016,
          "std_err": 0.0003272056348045319,
          "t_value": 5.794270535354964,
          "p_value": 7.96410515559308e-09
        },
        "auction_type:asynchronous": {
          "estimate": 0.00018217773437499715,
          "std_err": 0.000327205634804532,
          "t_value": 0.5567683285278004,
          "p_value": 0.5777486166100458
        },
        "auction_type:n_bidders": {
          "estimate": -0.0014388378906249912,
          "std_err": 0.000327205634804532,
          "t_value": -4.397350588062252,
          "p_value": 1.1538882154481855e-05
        },
        "auction_type:n_actions": {
          "estimate": 0.00013303710937500392,
          "std_err": 0.000327205634804532,
          "t_value": 0.4065856306370714,
          "p_value": 0.6843562726597292
        },
        "auction_type:info_feedback": {
          "estimate": 4.50292968750024e-05,
          "std_err": 0.000327205634804532,
          "t_value": 0.13761773051953174,
          "p_value": 0.8905565274255673
        },
        "auction_type:decay_type": {
          "estimate": 7.069335937500813e-05,
          "std_err": 0.000327205634804532,
          "t_value": 0.2160517786230648,
          "p_value": 0.8289696304854035
        },
        "alpha:gamma": {
          "estimate": -0.0005615136718749991,
          "std_err": 0.000327205634804532,
          "t_value": -1.7160880258386733,
          "p_value": 0.08630227741333377
        },
        "alpha:reserve_price": {
          "estimate": -0.0008498632812499994,
          "std_err": 0.000327205634804532,
          "t_value": -2.5973369369317116,
          "p_value": 0.009464532709048472
        },
        "alpha:init": {
          "estimate": -0.0009552734375000065,
          "std_err": 0.00032720563480453203,
          "t_value": -2.9194895682975424,
          "p_value": 0.0035456340756964203
        },
        "alpha:exploration": {
          "estimate": 0.0004878515624999981,
          "std_err": 0.0003272056348045319,
          "t_value": 1.490963206643534,
          "p_value": 0.13613036211388804
        },
        "alpha:asynchronous": {
          "estimate": -0.0004585253906249969,
          "std_err": 0.000327205634804532,
          "t_value": -1.4013370854658829,
          "p_value": 0.16126993692726616
        },
        "alpha:n_bidders": {
          "estimate": 0.0003814160156249919,
          "std_err": 0.000327205634804532,
          "t_value": 1.1656767948169489,
          "p_value": 0.24388547434004915
        },
        "alpha:n_actions": {
          "estimate": -0.00013284179687499402,
          "std_err": 0.0003272056348045319,
          "t_value": -0.40598872007308756,
          "p_value": 0.6847947362920512
        },
        "alpha:info_feedback": {
          "estimate": -0.00015108398437500522,
          "std_err": 0.000327205634804532,
          "t_value": -0.46174016674639684,
          "p_value": 0.6443183618103612
        },
        "alpha:decay_type": {
          "estimate": -0.00017858398437499008,
          "std_err": 0.000327205634804532,
          "t_value": -0.5457851741510309,
          "p_value": 0.5852750671591376
        },
        "gamma:reserve_price": {
          "estimate": 0.0014884765624999952,
          "std_err": 0.0003272056348045319,
          "t_value": 4.549055407891097,
          "p_value": 5.714941891013951e-06
        },
        "gamma:init": {
          "estimate": 0.0013811132812500005,
          "std_err": 0.0003272056348045319,
          "t_value": 4.220933670885767,
          "p_value": 2.5428974932461826e-05
        },
        "gamma:exploration": {
          "estimate": -0.001438007812500002,
          "std_err": 0.000327205634804532,
          "t_value": -4.394813718165482,
          "p_value": 1.167313616450373e-05
        },
        "gamma:asynchronous": {
          "estimate": 0.0009178222656250031,
          "std_err": 0.000327205634804532,
          "t_value": 2.8050319676594113,
          "p_value": 0.005080275039015421
        },
        "gamma:n_bidders": {
          "estimate": -0.00044729492187500926,
          "std_err": 0.000327205634804532,
          "t_value": -1.3670147280385831,
          "p_value": 0.17177578998132367
        },
        "gamma:n_actions": {
          "estimate": 0.00024674804687500483,
          "std_err": 0.000327205634804532,
          "t_value": 0.7541069609709156,
          "p_value": 0.4508746233833356
        },
        "gamma:info_feedback": {
          "estimate": 0.0003495410156249902,
          "std_err": 0.000327205634804532,
          "t_value": 1.0682609907797005,
          "p_value": 0.2855329558786688
        },
        "gamma:decay_type": {
          "estimate": 0.0003948925781250125,
          "std_err": 0.0003272056348045319,
          "t_value": 1.206863623729817,
          "p_value": 0.22762875936114443
        },
        "reserve_price:init": {
          "estimate": 0.0015503613281250008,
          "std_err": 0.0003272056348045319,
          "t_value": 4.738186520079842,
          "p_value": 2.309680561516076e-06
        },
        "reserve_price:exploration": {
          "estimate": 0.018307119140624998,
          "std_err": 0.000327205634804532,
          "t_value": 55.94988959026153,
          "p_value": 0.0
        },
        "reserve_price:asynchronous": {
          "estimate": 0.001183749999999987,
          "std_err": 0.000327205634804532,
          "t_value": 3.6177555460105153,
          "p_value": 0.00030461215165759117
        },
        "reserve_price:n_bidders": {
          "estimate": -0.02170249999999999,
          "std_err": 0.000327205634804532,
          "t_value": -66.32679175272992,
          "p_value": 0.0
        },
        "reserve_price:n_actions": {
          "estimate": 0.0022141015624999997,
          "std_err": 0.000327205634804532,
          "t_value": 6.766697535091878,
          "p_value": 1.729216741732981e-11
        },
        "reserve_price:info_feedback": {
          "estimate": 0.0005836523437500022,
          "std_err": 0.0003272056348045319,
          "t_value": 1.7837478382628345,
          "p_value": 0.07461768474308753
        },
        "reserve_price:decay_type": {
          "estimate": -0.002634863281250002,
          "std_err": 0.000327205634804532,
          "t_value": -8.05262196301733,
          "p_value": 1.3841614644045914e-15
        },
        "init:exploration": {
          "estimate": -0.0009586816406249952,
          "std_err": 0.00032720563480453203,
          "t_value": -2.9299056576385,
          "p_value": 0.00342942996807362
        },
        "init:asynchronous": {
          "estimate": 0.0010686523437500024,
          "std_err": 0.000327205634804532,
          "t_value": 3.2659961506726503,
          "p_value": 0.0011094133969152562
        },
        "init:n_bidders": {
          "estimate": -0.000418554687499999,
          "std_err": 0.0003272056348045319,
          "t_value": -1.2791793385527659,
          "p_value": 0.2009837216196989
        },
        "init:n_actions": {
          "estimate": 0.0002885742187500071,
          "std_err": 0.000327205634804532,
          "t_value": 0.8819353582416062,
          "p_value": 0.37791876109752376
        },
        "init:info_feedback": {
          "estimate": 0.0006358593750000074,
          "std_err": 0.000327205634804532,
          "t_value": 1.9433020320076726,
          "p_value": 0.05212114959061884
        },
        "init:decay_type": {
          "estimate": 0.0003505273437499943,
          "std_err": 0.000327205634804532,
          "t_value": 1.0712753891276792,
          "p_value": 0.2841761175659275
        },
        "exploration:asynchronous": {
          "estimate": -0.0008615429687500308,
          "std_err": 0.0003272056348045319,
          "t_value": -2.633032188656239,
          "p_value": 0.008528421087999985
        },
        "exploration:n_bidders": {
          "estimate": -0.01106970703125003,
          "std_err": 0.000327205634804532,
          "t_value": -33.831040342147276,
          "p_value": 2.05167870585768e-198
        },
        "exploration:n_actions": {
          "estimate": 0.0008882617187499879,
          "std_err": 0.000327205634804532,
          "t_value": 2.7146895538049733,
          "p_value": 0.006691335467288851
        },
        "exploration:info_feedback": {
          "estimate": -0.000342285156250023,
          "std_err": 0.000327205634804532,
          "t_value": -1.0460857633289211,
          "p_value": 0.2956490583401149
        },
        "exploration:decay_type": {
          "estimate": 0.0027421484375000143,
          "std_err": 0.0003272056348045319,
          "t_value": 8.380504935797134,
          "p_value": 9.85048848861329e-17
        },
        "asynchronous:n_bidders": {
          "estimate": -0.0003327050781250365,
          "std_err": 0.0003272056348045319,
          "t_value": -1.0168073001670337,
          "p_value": 0.30936927384593205
        },
        "asynchronous:n_actions": {
          "estimate": 0.0002697949218749674,
          "std_err": 0.0003272056348045319,
          "t_value": 0.8245424075173372,
          "p_value": 0.4097306971778132
        },
        "asynchronous:info_feedback": {
          "estimate": 0.0011988769531249782,
          "std_err": 0.000327205634804532,
          "t_value": 3.663986269188703,
          "p_value": 0.000254846114166143
        },
        "asynchronous:decay_type": {
          "estimate": 0.0003527050781250179,
          "std_err": 0.0003272056348045319,
          "t_value": 1.0779309419158352,
          "p_value": 0.28119581415801925
        },
        "n_bidders:n_actions": {
          "estimate": -0.0010661230468750151,
          "std_err": 0.000327205634804532,
          "t_value": -3.258266158869489,
          "p_value": 0.001139915046248603
        },
        "n_bidders:info_feedback": {
          "estimate": -7.470703125028125e-06,
          "std_err": 0.000327205634804532,
          "t_value": -0.022831829071314796,
          "p_value": 0.9817867181498585
        },
        "n_bidders:decay_type": {
          "estimate": 0.002012744140625003,
          "std_err": 0.0003272056348045319,
          "t_value": 6.151312589183827,
          "p_value": 9.271738872530537e-10
        },
        "n_actions:info_feedback": {
          "estimate": 2.4755859374990226e-05,
          "std_err": 0.000327205634804532,
          "t_value": 0.07565841398110099,
          "p_value": 0.9396985013888424
        },
        "n_actions:decay_type": {
          "estimate": -9.29589843749949e-05,
          "std_err": 0.000327205634804532,
          "t_value": -0.2840995829137456,
          "p_value": 0.7763637573090545
        },
        "info_feedback:decay_type": {
          "estimate": 0.00016528320312500337,
          "std_err": 0.0003272056348045319,
          "t_value": 0.5051355647458249,
          "p_value": 0.6135198137943884
        }
      }
    },
    "price_volatility": {
      "r_squared": 0.9056686581901815,
      "adj_r_squared": 0.9025258673979311,
      "f_statistic": 288.17338412197614,
      "f_pvalue": 0.0,
      "n_obs": 2048,
      "coefficients": {
        "auction_type": {
          "estimate": 0.0036332635845043133,
          "std_err": 0.000388051377869207,
          "t_value": 9.362841602198634,
          "p_value": 2.0346251588047596e-20
        },
        "alpha": {
          "estimate": -0.0006924428306161614,
          "std_err": 0.00038805137786920667,
          "t_value": -1.7844101840801874,
          "p_value": 0.07451003576027987
        },
        "gamma": {
          "estimate": 0.006562646336276283,
          "std_err": 0.0003880513778692067,
          "t_value": 16.91179753648042,
          "p_value": 4.8879893398156763e-60
        },
        "reserve_price": {
          "estimate": -0.024343737302816235,
          "std_err": 0.00038805137786920667,
          "t_value": -62.73328402153317,
          "p_value": 0.0
        },
        "init": {
          "estimate": 0.004359979073241462,
          "std_err": 0.0003880513778692066,
          "t_value": 11.235571684301558,
          "p_value": 1.9367853470518596e-28
        },
        "exploration": {
          "estimate": 0.027890656478168935,
          "std_err": 0.00038805137786920683,
          "t_value": 71.87361795058362,
          "p_value": 0.0
        },
        "asynchronous": {
          "estimate": 0.004549799952654943,
          "std_err": 0.00038805137786920645,
          "t_value": 11.724735981193868,
          "p_value": 9.623478636792494e-31
        },
        "n_bidders": {
          "estimate": -0.029071464564401864,
          "std_err": 0.00038805137786920667,
          "t_value": -74.91653482596432,
          "p_value": 0.0
        },
        "n_actions": {
          "estimate": -0.0016112558838983007,
          "std_err": 0.00038805137786920667,
          "t_value": -4.152171531372264,
          "p_value": 3.433046133282609e-05
        },
        "info_feedback": {
          "estimate": 0.0005276016454542724,
          "std_err": 0.0003880513778692067,
          "t_value": 1.3596180184988322,
          "p_value": 0.17410556259841073
        },
        "decay_type": {
          "estimate": -0.008287212319233388,
          "std_err": 0.0003880513778692067,
          "t_value": -21.355966740122245,
          "p_value": 3.065042514403268e-91
        },
        "auction_type:alpha": {
          "estimate": 0.00037442092793506747,
          "std_err": 0.0003880513778692067,
          "t_value": 0.9648746255998776,
          "p_value": 0.33472538118398765
        },
        "auction_type:gamma": {
          "estimate": 0.002064277653679447,
          "std_err": 0.0003880513778692067,
          "t_value": 5.319598824811324,
          "p_value": 1.1575258943644156e-07
        },
        "auction_type:reserve_price": {
          "estimate": -0.0010590617245824934,
          "std_err": 0.0003880513778692067,
          "t_value": -2.729179137045744,
          "p_value": 0.006405360645363594
        },
        "auction_type:init": {
          "estimate": -0.0006176695731473874,
          "std_err": 0.0003880513778692067,
          "t_value": -1.5917211183194762,
          "p_value": 0.11160692757093439
        },
        "auction_type:exploration": {
          "estimate": -0.0008384246212051849,
          "std_err": 0.00038805137786920667,
          "t_value": -2.1606020981267515,
          "p_value": 0.030845634321247397
        },
        "auction_type:asynchronous": {
          "estimate": 0.0004502285202416533,
          "std_err": 0.0003880513778692067,
          "t_value": 1.1602291498457287,
          "p_value": 0.2460953272739691
        },
        "auction_type:n_bidders": {
          "estimate": -0.0020535901195928544,
          "std_err": 0.0003880513778692067,
          "t_value": -5.2920572808403215,
          "p_value": 1.343354746214732e-07
        },
        "auction_type:n_actions": {
          "estimate": 0.000395744901264919,
          "std_err": 0.0003880513778692067,
          "t_value": 1.019826043236742,
          "p_value": 0.30793549633358686
        },
        "auction_type:info_feedback": {
          "estimate": -0.00032757532436305473,
          "std_err": 0.0003880513778692067,
          "t_value": -0.8441545193365206,
          "p_value": 0.3986849917115767
        },
        "auction_type:decay_type": {
          "estimate": 0.0022444019942515305,
          "std_err": 0.0003880513778692067,
          "t_value": 5.783775351025836,
          "p_value": 8.468714497317636e-09
        },
        "alpha:gamma": {
          "estimate": -0.0011972682687029328,
          "std_err": 0.0003880513778692067,
          "t_value": -3.085334409265965,
          "p_value": 0.002061343121871343
        },
        "alpha:reserve_price": {
          "estimate": 0.00019150734038993834,
          "std_err": 0.0003880513778692067,
          "t_value": 0.4935102703191178,
          "p_value": 0.6217067908780758
        },
        "alpha:init": {
          "estimate": -0.0016013468279423024,
          "std_err": 0.0003880513778692067,
          "t_value": -4.126636108690841,
          "p_value": 3.833543498820239e-05
        },
        "alpha:exploration": {
          "estimate": 0.00037469708065398843,
          "std_err": 0.00038805137786920667,
          "t_value": 0.9655862651782174,
          "p_value": 0.33436910952566534
        },
        "alpha:asynchronous": {
          "estimate": -0.0007923982598778323,
          "std_err": 0.0003880513778692067,
          "t_value": -2.041993161392436,
          "p_value": 0.04128439963764473
        },
        "alpha:n_bidders": {
          "estimate": -0.0007837467173486871,
          "std_err": 0.0003880513778692067,
          "t_value": -2.01969832358861,
          "p_value": 0.04354909158895312
        },
        "alpha:n_actions": {
          "estimate": -0.0002707620233807489,
          "std_err": 0.00038805137786920667,
          "t_value": -0.6977478726335297,
          "p_value": 0.48541676826350977
        },
        "alpha:info_feedback": {
          "estimate": 0.0009057206938479827,
          "std_err": 0.0003880513778692067,
          "t_value": 2.3340226204615027,
          "p_value": 0.019694056859342664
        },
        "alpha:decay_type": {
          "estimate": -0.00043853129757002367,
          "std_err": 0.0003880513778692067,
          "t_value": -1.1300856602494302,
          "p_value": 0.25857693966441625
        },
        "gamma:reserve_price": {
          "estimate": -0.0016756779986746577,
          "std_err": 0.00038805137786920667,
          "t_value": -4.31818592650236,
          "p_value": 1.650857302153477e-05
        },
        "gamma:init": {
          "estimate": 0.003961514436208511,
          "std_err": 0.00038805137786920667,
          "t_value": 10.208736940869068,
          "p_value": 6.989753563421538e-24
        },
        "gamma:exploration": {
          "estimate": -0.0066840135378640475,
          "std_err": 0.0003880513778692067,
          "t_value": -17.224558187542126,
          "p_value": 4.582644932904559e-62
        },
        "gamma:asynchronous": {
          "estimate": 0.0033085975232110326,
          "std_err": 0.0003880513778692067,
          "t_value": 8.526184190811454,
          "p_value": 2.952759310564192e-17
        },
        "gamma:n_bidders": {
          "estimate": 0.00016428691026703734,
          "std_err": 0.0003880513778692067,
          "t_value": 0.42336381117659755,
          "p_value": 0.6720758017070904
        },
        "gamma:n_actions": {
          "estimate": -0.00057049977526266,
          "std_err": 0.0003880513778692067,
          "t_value": -1.4701655703306065,
          "p_value": 0.14167571808273044
        },
        "gamma:info_feedback": {
          "estimate": -0.00012670352867646853,
          "std_err": 0.0003880513778692067,
          "t_value": -0.3265122504452854,
          "p_value": 0.7440713135441264
        },
        "gamma:decay_type": {
          "estimate": 0.0019539893382607277,
          "std_err": 0.00038805137786920667,
          "t_value": 5.035388223564878,
          "p_value": 5.200768009101544e-07
        },
        "reserve_price:init": {
          "estimate": -0.0015144300544505886,
          "std_err": 0.00038805137786920667,
          "t_value": -3.9026534650291325,
          "p_value": 9.832356888528839e-05
        },
        "reserve_price:exploration": {
          "estimate": -0.002846242353428245,
          "std_err": 0.0003880513778692067,
          "t_value": -7.334704927623205,
          "p_value": 3.223630735696833e-13
        },
        "reserve_price:asynchronous": {
          "estimate": -0.0012001755573886,
          "std_err": 0.0003880513778692067,
          "t_value": -3.092826429270201,
          "p_value": 0.0020102556654164818
        },
        "reserve_price:n_bidders": {
          "estimate": 0.013184175684313782,
          "std_err": 0.0003880513778692067,
          "t_value": 33.97533531953474,
          "p_value": 9.2566860884081e-200
        },
        "reserve_price:n_actions": {
          "estimate": -0.0004785223272350892,
          "std_err": 0.0003880513778692067,
          "t_value": -1.233141677946511,
          "p_value": 0.2176692147237054
        },
        "reserve_price:info_feedback": {
          "estimate": -0.0006935428308651737,
          "std_err": 0.00038805137786920667,
          "t_value": -1.7872448609084268,
          "p_value": 0.07405075839542677
        },
        "reserve_price:decay_type": {
          "estimate": 0.000931026513407664,
          "std_err": 0.0003880513778692067,
          "t_value": 2.3992351696312437,
          "p_value": 0.016521240094127455
        },
        "init:exploration": {
          "estimate": -0.0032169064340097104,
          "std_err": 0.0003880513778692067,
          "t_value": -8.289898238923335,
          "p_value": 2.064279333376506e-16
        },
        "init:asynchronous": {
          "estimate": 0.003303651008319076,
          "std_err": 0.0003880513778692067,
          "t_value": 8.513437129020003,
          "p_value": 3.283495633488711e-17
        },
        "init:n_bidders": {
          "estimate": 0.0014676399652497106,
          "std_err": 0.00038805137786920667,
          "t_value": 3.7820764180983812,
          "p_value": 0.00016013633789367367
        },
        "init:n_actions": {
          "estimate": 0.0003186937695525819,
          "std_err": 0.0003880513778692067,
          "t_value": 0.821266944863157,
          "p_value": 0.411593053169369
        },
        "init:info_feedback": {
          "estimate": 0.0021670874765843755,
          "std_err": 0.0003880513778692067,
          "t_value": 5.584537512748622,
          "p_value": 2.66635396717828e-08
        },
        "init:decay_type": {
          "estimate": 0.0012413593472863555,
          "std_err": 0.0003880513778692067,
          "t_value": 3.1989561642653346,
          "p_value": 0.0014010557992319723
        },
        "exploration:asynchronous": {
          "estimate": -0.0044729761026274335,
          "std_err": 0.00038805137786920667,
          "t_value": -11.526762582801748,
          "p_value": 8.430852987624189e-30
        },
        "exploration:n_bidders": {
          "estimate": 0.006175611363408049,
          "std_err": 0.0003880513778692067,
          "t_value": 15.91441679016418,
          "p_value": 9.332300181414976e-54
        },
        "exploration:n_actions": {
          "estimate": -0.002999109049489933,
          "std_err": 0.0003880513778692067,
          "t_value": -7.728639094024263,
          "p_value": 1.7153184952044946e-14
        },
        "exploration:info_feedback": {
          "estimate": -0.0004725231789866535,
          "std_err": 0.0003880513778692067,
          "t_value": -1.2176820027834512,
          "p_value": 0.2234898589845071
        },
        "exploration:decay_type": {
          "estimate": 0.008237616815586745,
          "std_err": 0.00038805137786920667,
          "t_value": 21.228160200898056,
          "p_value": 2.820214533200121e-90
        },
        "asynchronous:n_bidders": {
          "estimate": 0.0005104559315705485,
          "std_err": 0.00038805137786920667,
          "t_value": 1.3154338850011724,
          "p_value": 0.1885163480399415
        },
        "asynchronous:n_actions": {
          "estimate": -6.115627731595246e-05,
          "std_err": 0.00038805137786920667,
          "t_value": -0.15759840269544226,
          "p_value": 0.8747893236217953
        },
        "asynchronous:info_feedback": {
          "estimate": 0.004485286663430579,
          "std_err": 0.0003880513778692067,
          "t_value": 11.55848663148505,
          "p_value": 5.967088665306896e-30
        },
        "asynchronous:decay_type": {
          "estimate": 0.0010248729737578417,
          "std_err": 0.00038805137786920667,
          "t_value": 2.6410754663091978,
          "p_value": 0.008329282622280736
        },
        "n_bidders:n_actions": {
          "estimate": 0.001068135727256083,
          "std_err": 0.0003880513778692067,
          "t_value": 2.7525626454961327,
          "p_value": 0.005967000309815241
        },
        "n_bidders:info_feedback": {
          "estimate": 0.0020173068230467626,
          "std_err": 0.0003880513778692067,
          "t_value": 5.198556011123607,
          "p_value": 2.2152578409394266e-07
        },
        "n_bidders:decay_type": {
          "estimate": 4.965381344155693e-05,
          "std_err": 0.00038805137786920667,
          "t_value": 0.12795680230336104,
          "p_value": 0.8981961463153632
        },
        "n_actions:info_feedback": {
          "estimate": 7.694243655784194e-05,
          "std_err": 0.0003880513778692067,
          "t_value": 0.19827899331354906,
          "p_value": 0.8428471311384776
        },
        "n_actions:decay_type": {
          "estimate": 0.000544201148375026,
          "std_err": 0.0003880513778692067,
          "t_value": 1.40239457816962,
          "p_value": 0.16095413478053489
        },
        "info_feedback:decay_type": {
          "estimate": -0.0002292078585307679,
          "std_err": 0.00038805137786920667,
          "t_value": -0.5906636894046097,
          "p_value": 0.5548131591371535
        }
      }
    },
    "winner_entropy": {
      "r_squared": 0.9993427655169714,
      "adj_r_squared": 0.9993208687598387,
      "f_statistic": 45638.84777369116,
      "f_pvalue": 0.0,
      "n_obs": 2048,
      "coefficients": {
        "auction_type": {
          "estimate": 0.0017562864182047704,
          "std_err": 0.00020044028201081937,
          "t_value": 8.762143021281368,
          "p_value": 4.031701043566076e-18
        },
        "alpha": {
          "estimate": 0.0009300822212131142,
          "std_err": 0.0002004402820108192,
          "t_value": 4.640196131648382,
          "p_value": 3.7086114099810604e-06
        },
        "gamma": {
          "estimate": -0.001156695213170637,
          "std_err": 0.00020044028201081924,
          "t_value": -5.770772229846502,
          "p_value": 9.13718120905974e-09
        },
        "reserve_price": {
          "estimate": -6.615101758759007e-05,
          "std_err": 0.0002004402820108192,
          "t_value": -0.33002855974838147,
          "p_value": 0.7414132776276706
        },
        "init": {
          "estimate": 0.0005746744589149413,
          "std_err": 0.00020044028201081918,
          "t_value": 2.867060718283773,
          "p_value": 0.004186821979914051
        },
        "exploration": {
          "estimate": 0.0019074530165597986,
          "std_err": 0.0002004402820108193,
          "t_value": 9.51631576958587,
          "p_value": 5.009393047407481e-21
        },
        "asynchronous": {
          "estimate": -0.0007396917037371664,
          "std_err": 0.0002004402820108191,
          "t_value": -3.690334579040556,
          "p_value": 0.00023000717031230227
        },
        "n_bidders": {
          "estimate": 0.3478399437494333,
          "std_err": 0.0002004402820108192,
          "t_value": 1735.3794370068679,
          "p_value": 0.0
        },
        "n_actions": {
          "estimate": -0.0003079404525966889,
          "std_err": 0.0002004402820108192,
          "t_value": -1.5363201922658796,
          "p_value": 0.12461956239035896
        },
        "info_feedback": {
          "estimate": 0.0005787733486125324,
          "std_err": 0.00020044028201081924,
          "t_value": 2.8875101491889326,
          "p_value": 0.00392515484020014
        },
        "decay_type": {
          "estimate": -0.00040668770145622566,
          "std_err": 0.00020044028201081924,
          "t_value": -2.0289719081231072,
          "p_value": 0.04259464129742074
        },
        "auction_type:alpha": {
          "estimate": -0.0005635599446994717,
          "std_err": 0.00020044028201081924,
          "t_value": -2.811610216498559,
          "p_value": 0.004977952796024939
        },
        "auction_type:gamma": {
          "estimate": 0.0007574314677782983,
          "std_err": 0.00020044028201081924,
          "t_value": 3.778838565680197,
          "p_value": 0.00016221741115682246
        },
        "auction_type:reserve_price": {
          "estimate": -6.718825221820266e-06,
          "std_err": 0.00020044028201081924,
          "t_value": -0.03352033410857804,
          "p_value": 0.9732630275842871
        },
        "auction_type:init": {
          "estimate": -0.0002672504268179622,
          "std_err": 0.00020044028201081924,
          "t_value": -1.3333169567359555,
          "p_value": 0.18258110819759277
        },
        "auction_type:exploration": {
          "estimate": -0.001505118765536088,
          "std_err": 0.0002004402820108192,
          "t_value": -7.509063300234461,
          "p_value": 8.952797495406192e-14
        },
        "auction_type:asynchronous": {
          "estimate": 0.00049728259466898,
          "std_err": 0.00020044028201081924,
          "t_value": 2.480951382028778,
          "p_value": 0.013185671230195454
        },
        "auction_type:n_bidders": {
          "estimate": -0.0013167714385403455,
          "std_err": 0.00020044028201081924,
          "t_value": -6.569395259927192,
          "p_value": 6.437519400668753e-11
        },
        "auction_type:n_actions": {
          "estimate": 5.218604660590817e-05,
          "std_err": 0.00020044028201081924,
          "t_value": 0.26035708033523575,
          "p_value": 0.7946154048115871
        },
        "auction_type:info_feedback": {
          "estimate": -0.0006831026144934092,
          "std_err": 0.00020044028201081924,
          "t_value": -3.40801064357182,
          "p_value": 0.0006674744500178556
        },
        "auction_type:decay_type": {
          "estimate": 0.00023677987822981226,
          "std_err": 0.00020044028201081924,
          "t_value": 1.1812988679442764,
          "p_value": 0.2376258131477002
        },
        "alpha:gamma": {
          "estimate": 0.0008958470668039582,
          "std_err": 0.00020044028201081924,
          "t_value": 4.469396359937284,
          "p_value": 8.287134846819522e-06
        },
        "alpha:reserve_price": {
          "estimate": 0.00022495810568215556,
          "std_err": 0.00020044028201081924,
          "t_value": 1.1223198422261893,
          "p_value": 0.2618624812647853
        },
        "alpha:init": {
          "estimate": -0.0002125876746023058,
          "std_err": 0.00020044028201081924,
          "t_value": -1.0606035496938229,
          "p_value": 0.28899939773799205
        },
        "alpha:exploration": {
          "estimate": -0.001175792294971062,
          "std_err": 0.0002004402820108192,
          "t_value": -5.8660478980347674,
          "p_value": 5.217729835257248e-09
        },
        "alpha:asynchronous": {
          "estimate": 0.00022657646195007328,
          "std_err": 0.00020044028201081924,
          "t_value": 1.1303938493652852,
          "p_value": 0.2584471443590342
        },
        "alpha:n_bidders": {
          "estimate": -0.0003829023076678599,
          "std_err": 0.00020044028201081924,
          "t_value": -1.910306171127777,
          "p_value": 0.056238053697830644
        },
        "alpha:n_actions": {
          "estimate": 0.00017493882504147093,
          "std_err": 0.0002004402820108192,
          "t_value": 0.8727727944028147,
          "p_value": 0.38289270517757024
        },
        "alpha:info_feedback": {
          "estimate": -0.000552132326455251,
          "std_err": 0.00020044028201081924,
          "t_value": -2.7545976333512057,
          "p_value": 0.005930161440186831
        },
        "alpha:decay_type": {
          "estimate": 0.0001687199383606857,
          "std_err": 0.00020044028201081924,
          "t_value": 0.8417466622381755,
          "p_value": 0.400031373854029
        },
        "gamma:reserve_price": {
          "estimate": -7.041735620564689e-05,
          "std_err": 0.0002004402820108192,
          "t_value": -0.35131339618573254,
          "p_value": 0.7253906055575299
        },
        "gamma:init": {
          "estimate": 0.0005620469105974305,
          "std_err": 0.0002004402820108192,
          "t_value": 2.804061663448931,
          "p_value": 0.005095527737400776
        },
        "gamma:exploration": {
          "estimate": 0.0009058884138789401,
          "std_err": 0.00020044028201081924,
          "t_value": 4.519492812477896,
          "p_value": 6.564567791496596e-06
        },
        "gamma:asynchronous": {
          "estimate": -0.0004601122675304342,
          "std_err": 0.00020044028201081924,
          "t_value": -2.2955079832984797,
          "p_value": 0.021808065546178694
        },
        "gamma:n_bidders": {
          "estimate": 0.0005712453768470971,
          "std_err": 0.00020044028201081924,
          "t_value": 2.849952969115573,
          "p_value": 0.004417787873657447
        },
        "gamma:n_actions": {
          "estimate": -0.0001267968080428287,
          "std_err": 0.00020044028201081924,
          "t_value": -0.6325914470424889,
          "p_value": 0.5270734809875595
        },
        "gamma:info_feedback": {
          "estimate": 0.00032661856410743615,
          "std_err": 0.00020044028201081924,
          "t_value": 1.6295056105030132,
          "p_value": 0.10336501485816782
        },
        "gamma:decay_type": {
          "estimate": -0.0002128306122425815,
          "std_err": 0.0002004402820108192,
          "t_value": -1.0618155697420817,
          "p_value": 0.28844884699425954
        },
        "reserve_price:init": {
          "estimate": -0.0001860343934550898,
          "std_err": 0.0002004402820108192,
          "t_value": -0.9281287752581,
          "p_value": 0.3534538432176756
        },
        "reserve_price:exploration": {
          "estimate": 0.0003152836259230067,
          "std_err": 0.00020044028201081924,
          "t_value": 1.5729554097613399,
          "p_value": 0.11588883009586709
        },
        "reserve_price:asynchronous": {
          "estimate": 0.0002311262420231246,
          "std_err": 0.00020044028201081924,
          "t_value": 1.1530927800762574,
          "p_value": 0.2490114161851818
        },
        "reserve_price:n_bidders": {
          "estimate": 6.684251990624248e-05,
          "std_err": 0.00020044028201081924,
          "t_value": 0.3334784766598687,
          "p_value": 0.7388084260278986
        },
        "reserve_price:n_actions": {
          "estimate": 0.00012602652145230414,
          "std_err": 0.00020044028201081924,
          "t_value": 0.628748474049251,
          "p_value": 0.5295862256453099
        },
        "reserve_price:info_feedback": {
          "estimate": -0.00012417014259811894,
          "std_err": 0.0002004402820108192,
          "t_value": -0.6194869681505266,
          "p_value": 0.5356668434458521
        },
        "reserve_price:decay_type": {
          "estimate": -3.267030174532955e-05,
          "std_err": 0.00020044028201081924,
          "t_value": -0.16299269496919833,
          "p_value": 0.8705408110376462
        },
        "init:exploration": {
          "estimate": -0.0003235230766020668,
          "std_err": 0.00020044028201081924,
          "t_value": -1.6140621703206537,
          "p_value": 0.10667320190097888
        },
        "init:asynchronous": {
          "estimate": 0.0005197733561636212,
          "std_err": 0.00020044028201081924,
          "t_value": 2.5931581763368565,
          "p_value": 0.009579911036506964
        },
        "init:n_bidders": {
          "estimate": -0.00042683646250695774,
          "std_err": 0.0002004402820108192,
          "t_value": -2.129494422103828,
          "p_value": 0.033336358463955384
        },
        "init:n_actions": {
          "estimate": -0.0001448519129920326,
          "std_err": 0.00020044028201081924,
          "t_value": -0.722668674873516,
          "p_value": 0.4699687699462287
        },
        "init:info_feedback": {
          "estimate": 0.0005039988340908652,
          "std_err": 0.00020044028201081924,
          "t_value": 2.514458815537192,
          "p_value": 0.01200017972689377
        },
        "init:decay_type": {
          "estimate": 0.00022116958244224315,
          "std_err": 0.00020044028201081924,
          "t_value": 1.1034188348942007,
          "p_value": 0.2699793393634966
        },
        "exploration:asynchronous": {
          "estimate": 0.0004889509233677418,
          "std_err": 0.0002004402820108192,
          "t_value": 2.439384531205906,
          "p_value": 0.01479952110621203
        },
        "exploration:n_bidders": {
          "estimate": -0.001022207037372276,
          "std_err": 0.00020044028201081924,
          "t_value": -5.099808417337489,
          "p_value": 3.7240686097368743e-07
        },
        "exploration:n_actions": {
          "estimate": 0.00021365830679707584,
          "std_err": 0.00020044028201081924,
          "t_value": 1.0659449520508215,
          "p_value": 0.28657842179068593
        },
        "exploration:info_feedback": {
          "estimate": -0.0008295661614370342,
          "std_err": 0.00020044028201081924,
          "t_value": -4.138719787833148,
          "p_value": 3.6387859738925135e-05
        },
        "exploration:decay_type": {
          "estimate": 0.00030867684339186424,
          "std_err": 0.0002004402820108192,
          "t_value": 1.5399940585555687,
          "p_value": 0.12372150994520625
        },
        "asynchronous:n_bidders": {
          "estimate": 0.0004978228717663243,
          "std_err": 0.0002004402820108192,
          "t_value": 2.483646833721044,
          "p_value": 0.01308661086376804
        },
        "asynchronous:n_actions": {
          "estimate": 0.00012708101143332415,
          "std_err": 0.0002004402820108192,
          "t_value": 0.6340093426253745,
          "p_value": 0.5261479238665568
        },
        "asynchronous:info_feedback": {
          "estimate": -0.0004840574864120317,
          "std_err": 0.00020044028201081924,
          "t_value": -2.4149710904213535,
          "p_value": 0.015826506453655215
        },
        "asynchronous:decay_type": {
          "estimate": -0.0003669296043999156,
          "std_err": 0.0002004402820108192,
          "t_value": -1.8306180809509625,
          "p_value": 0.06730772066272145
        },
        "n_bidders:n_actions": {
          "estimate": 2.0809877096961138e-05,
          "std_err": 0.00020044028201081924,
          "t_value": 0.10382083325864547,
          "p_value": 0.9173220424215438
        },
        "n_bidders:info_feedback": {
          "estimate": -0.00021259575624327232,
          "std_err": 0.00020044028201081924,
          "t_value": -1.0606438691390234,
          "p_value": 0.2889810715554662
        },
        "n_bidders:decay_type": {
          "estimate": 0.0004205353546701475,
          "std_err": 0.0002004402820108192,
          "t_value": 2.098058087183534,
          "p_value": 0.03602639114878088
        },
        "n_actions:info_feedback": {
          "estimate": 0.0002835465334759396,
          "std_err": 0.00020044028201081924,
          "t_value": 1.4146185119647483,
          "p_value": 0.15733753268971237
        },
        "n_actions:decay_type": {
          "estimate": -5.545296672211033e-05,
          "std_err": 0.00020044028201081924,
          "t_value": -0.2766558007492582,
          "p_value": 0.7820732747531463
        },
        "info_feedback:decay_type": {
          "estimate": -0.00010546679124636893,
          "std_err": 0.0002004402820108192,
          "t_value": -0.5261756279143337,
          "p_value": 0.5988250861401543
        }
      }
    }
  }
}